{
  "msg": {
    "initial-populations": 3,
    "start-at": "2019-02-05T12:15:34.003159+01:00",
    "threads": 2,
    "population-size": 256,
    "generations": 16,
    "length": 64
  },
  "time": "2019-02-05T12:15:34.009731+01:00"
}
{
  "msg": {
    "best": 50,
    "id": 4
  },
  "time": "2019-02-05T12:15:37.826445+01:00"
}
{
  "msg": {
    "id": 6,
    "best": 51
  },
  "time": "2019-02-05T12:15:38.108914+01:00"
}
{
  "msg": {
    "best": 50,
    "id": 6
  },
  "time": "2019-02-05T12:15:41.879770+01:00"
}
{
  "msg": {
    "best": 50,
    "id": 4
  },
  "time": "2019-02-05T12:15:42.109859+01:00"
}
{
  "time": "2019-02-05T12:15:45.642337+01:00",
  "msg": {
    "id": 4,
    "best": 55
  }
}
{
  "time": "2019-02-05T12:15:46.879703+01:00",
  "msg": {
    "best": 55,
    "id": 6
  }
}
{
  "msg": {
    "best": 57,
    "id": 7
  },
  "time": "2019-02-05T12:15:49.531387+01:00"
}
{
  "msg": {
    "best": 57,
    "id": 6
  },
  "time": "2019-02-05T12:15:51.382515+01:00"
}
{
  "msg": {
    "id": 4,
    "best": 58
  },
  "time": "2019-02-05T12:15:53.744433+01:00"
}
{
  "msg": {
    "id": 6,
    "best": 60
  },
  "time": "2019-02-05T12:15:55.689292+01:00"
}
{
  "msg": {
    "best": 60,
    "id": 7
  },
  "time": "2019-02-05T12:15:58.134268+01:00"
}
{
  "msg": {
    "best": 61,
    "id": 6
  },
  "time": "2019-02-05T12:15:59.570173+01:00"
}
{
  "msg": {
    "id": 4,
    "best": 61
  },
  "time": "2019-02-05T12:16:02.549847+01:00"
}
{
  "time": "2019-02-05T12:16:03.962417+01:00",
  "msg": {
    "id": 7,
    "best": 61
  }
}
{
  "msg": {
    "best": 61,
    "id": 6
  },
  "time": "2019-02-05T12:16:06.853257+01:00"
}
{
  "msg": {
    "id": 4,
    "best": 62
  },
  "time": "2019-02-05T12:16:08.357936+01:00"
}
{
  "time": "2019-02-05T12:16:10.873910+01:00",
  "msg": {
    "best": 62,
    "id": 7
  }
}
{
  "time": "2019-02-05T12:16:12.216389+01:00",
  "msg": {
    "id": 4,
    "best": 62
  }
}
{
  "msg": {
    "id": 6,
    "best": 62
  },
  "time": "2019-02-05T12:16:14.774127+01:00"
}
{
  "time": "2019-02-05T12:16:16.150326+01:00",
  "msg": {
    "best": 62,
    "id": 4
  }
}
{
  "msg": {
    "best": 62,
    "id": 7
  },
  "time": "2019-02-05T12:16:19.484372+01:00"
}
{
  "msg": {
    "best": 62,
    "id": 4
  },
  "time": "2019-02-05T12:16:20.601488+01:00"
}
{
  "time": "2019-02-05T12:16:24.334404+01:00",
  "msg": {
    "id": 6,
    "best": 62
  }
}
{
  "time": "2019-02-05T12:16:25.194693+01:00",
  "msg": {
    "id": 4,
    "best": 62
  }
}
{
  "msg": {
    "best": 63,
    "id": 6
  },
  "time": "2019-02-05T12:16:29.549159+01:00"
}
{
  "msg": {
    "best": 63,
    "id": 4
  },
  "time": "2019-02-05T12:16:30.359283+01:00"
}
{
  "time": "2019-02-05T12:16:34.342173+01:00",
  "msg": {
    "best": 63,
    "id": 4
  }
}
{
  "time": "2019-02-05T12:16:34.553137+01:00",
  "msg": {
    "id": 7,
    "best": 63
  }
}
{
  "msg": {
    "id": 6,
    "best": 63
  },
  "time": "2019-02-05T12:16:38.773383+01:00"
}
{
  "time": "2019-02-05T12:16:39.110591+01:00",
  "msg": {
    "id": 4,
    "best": 63
  }
}
{
  "msg": {
    "id": 6,
    "best": 63
  },
  "time": "2019-02-05T12:16:43.610270+01:00"
}
{
  "msg": {
    "best": 63,
    "id": 7
  },
  "time": "2019-02-05T12:16:43.957086+01:00"
}
{
  "msg": {
    "id": 4,
    "best": 63
  },
  "time": "2019-02-05T12:16:48.462482+01:00"
}
{
  "msg": {
    "best": 63,
    "id": 6
  },
  "time": "2019-02-05T12:16:48.893856+01:00"
}
{
  "time": "2019-02-05T12:16:52.781388+01:00",
  "msg": {
    "id": 7,
    "finishing-at": "2019-02-05T12:16:52.779285+01:00",
    "best": 64,
    "found": true
  }
}
{
  "time": "2019-02-05T12:16:54.020084+01:00",
  "msg": {
    "id": 4,
    "best": 63
  }
}
