{
  "msg": {
    "start-at": "2019-02-05T18:09:00.601713+01:00",
    "initial-populations": 12.0,
    "population-size": 256,
    "threads": 8,
    "length": 64,
    "generations": 16
  },
  "time": "2019-02-05T18:09:00.606161+01:00"
}
{
  "msg": {
    "best": 49,
    "id": 6
  },
  "time": "2019-02-05T18:09:09.288668+01:00"
}
{
  "msg": {
    "id": 4,
    "best": 49
  },
  "time": "2019-02-05T18:09:09.374457+01:00"
}
{
  "time": "2019-02-05T18:09:09.390095+01:00",
  "msg": {
    "best": 49,
    "id": 11
  }
}
{
  "msg": {
    "id": 12,
    "best": 49
  },
  "time": "2019-02-05T18:09:09.728044+01:00"
}
{
  "time": "2019-02-05T18:09:09.799394+01:00",
  "msg": {
    "id": 7,
    "best": 43
  }
}
{
  "msg": {
    "best": 43,
    "id": 10
  },
  "time": "2019-02-05T18:09:09.817581+01:00"
}
{
  "time": "2019-02-05T18:09:09.946004+01:00",
  "msg": {
    "best": 39,
    "id": 8
  }
}
{
  "time": "2019-02-05T18:09:09.961973+01:00",
  "msg": {
    "id": 9,
    "best": 39
  }
}
{
  "time": "2019-02-05T18:09:18.280061+01:00",
  "msg": {
    "id": 11,
    "best": 55
  }
}
{
  "msg": {
    "best": 55,
    "id": 4
  },
  "time": "2019-02-05T18:09:18.493139+01:00"
}
{
  "msg": {
    "id": 6,
    "best": 56
  },
  "time": "2019-02-05T18:09:18.664245+01:00"
}
{
  "msg": {
    "best": 56,
    "id": 12
  },
  "time": "2019-02-05T18:09:18.849545+01:00"
}
{
  "time": "2019-02-05T18:09:19.115777+01:00",
  "msg": {
    "best": 53,
    "id": 10
  }
}
{
  "time": "2019-02-05T18:09:19.121465+01:00",
  "msg": {
    "id": 7,
    "best": 53
  }
}
{
  "msg": {
    "best": 44,
    "id": 8
  },
  "time": "2019-02-05T18:09:19.589834+01:00"
}
{
  "msg": {
    "id": 9,
    "best": 44
  },
  "time": "2019-02-05T18:09:19.674550+01:00"
}
{
  "msg": {
    "best": 59,
    "id": 11
  },
  "time": "2019-02-05T18:09:28.018199+01:00"
}
{
  "time": "2019-02-05T18:09:28.150831+01:00",
  "msg": {
    "best": 60,
    "id": 4
  }
}
{
  "msg": {
    "id": 6,
    "best": 60
  },
  "time": "2019-02-05T18:09:28.240907+01:00"
}
{
  "time": "2019-02-05T18:09:28.421904+01:00",
  "msg": {
    "best": 60,
    "id": 12
  }
}
{
  "msg": {
    "id": 10,
    "best": 59
  },
  "time": "2019-02-05T18:09:28.706857+01:00"
}
{
  "time": "2019-02-05T18:09:28.979495+01:00",
  "msg": {
    "best": 56,
    "id": 7
  }
}
{
  "msg": {
    "best": 60,
    "id": 8
  },
  "time": "2019-02-05T18:09:29.379597+01:00"
}
{
  "time": "2019-02-05T18:09:29.577929+01:00",
  "msg": {
    "best": 60,
    "id": 9
  }
}
{
  "time": "2019-02-05T18:09:37.594085+01:00",
  "msg": {
    "id": 4,
    "best": 62
  }
}
{
  "time": "2019-02-05T18:09:37.774245+01:00",
  "msg": {
    "best": 60,
    "id": 6
  }
}
{
  "msg": {
    "best": 62,
    "id": 11
  },
  "time": "2019-02-05T18:09:37.956151+01:00"
}
{
  "msg": {
    "id": 12,
    "best": 62
  },
  "time": "2019-02-05T18:09:38.018621+01:00"
}
{
  "msg": {
    "id": 10,
    "best": 61
  },
  "time": "2019-02-05T18:09:38.304327+01:00"
}
{
  "msg": {
    "id": 7,
    "best": 62
  },
  "time": "2019-02-05T18:09:38.727813+01:00"
}
{
  "msg": {
    "id": 9,
    "best": 62
  },
  "time": "2019-02-05T18:09:39.467522+01:00"
}
{
  "msg": {
    "best": 62,
    "id": 8
  },
  "time": "2019-02-05T18:09:39.683980+01:00"
}
{
  "msg": {
    "best": 62,
    "id": 6
  },
  "time": "2019-02-05T18:09:47.698252+01:00"
}
{
  "time": "2019-02-05T18:09:47.741158+01:00",
  "msg": {
    "best": 62,
    "id": 4
  }
}
{
  "msg": {
    "best": 60,
    "id": 11
  },
  "time": "2019-02-05T18:09:48.024162+01:00"
}
{
  "time": "2019-02-05T18:09:48.201068+01:00",
  "msg": {
    "id": 12,
    "best": 62
  }
}
{
  "time": "2019-02-05T18:09:48.491255+01:00",
  "msg": {
    "best": 62,
    "id": 10
  }
}
{
  "msg": {
    "best": 63,
    "id": 7
  },
  "time": "2019-02-05T18:09:48.693534+01:00"
}
{
  "msg": {
    "id": 9,
    "best": 63
  },
  "time": "2019-02-05T18:09:49.304335+01:00"
}
{
  "time": "2019-02-05T18:09:49.497485+01:00",
  "msg": {
    "id": 8,
    "best": 61
  }
}
{
  "msg": {
    "best": 63,
    "id": 6
  },
  "time": "2019-02-05T18:09:57.432202+01:00"
}
{
  "msg": {
    "id": 4,
    "best": 63
  },
  "time": "2019-02-05T18:09:57.666055+01:00"
}
{
  "msg": {
    "id": 12,
    "best": 63
  },
  "time": "2019-02-05T18:09:57.901527+01:00"
}
{
  "msg": {
    "id": 11,
    "best": 63
  },
  "time": "2019-02-05T18:09:58.144167+01:00"
}
{
  "msg": {
    "best": 63,
    "id": 10
  },
  "time": "2019-02-05T18:09:58.312474+01:00"
}
{
  "msg": {
    "id": 4,
    "best": 63
  },
  "time": "2019-02-05T18:09:58.431367+01:00"
}
{
  "msg": {
    "best": 63,
    "id": 7
  },
  "time": "2019-02-05T18:09:58.764539+01:00"
}
{
  "time": "2019-02-05T18:09:59.407481+01:00",
  "msg": {
    "id": 9,
    "best": 63
  }
}
{
  "msg": {
    "best": 63,
    "id": 8
  },
  "time": "2019-02-05T18:09:59.613493+01:00"
}
{
  "time": "2019-02-05T18:10:00.181779+01:00",
  "msg": {
    "id": 9,
    "best": 63
  }
}
{
  "msg": {
    "id": 8,
    "best": 63
  },
  "time": "2019-02-05T18:10:00.384694+01:00"
}
{
  "msg": {
    "id": 8,
    "best": 63
  },
  "time": "2019-02-05T18:10:03.302192+01:00"
}
{
  "time": "2019-02-05T18:10:07.558518+01:00",
  "msg": {
    "id": 6,
    "best": 63
  }
}
{
  "msg": {
    "best": 63,
    "id": 12
  },
  "time": "2019-02-05T18:10:07.863648+01:00"
}
{
  "time": "2019-02-05T18:10:08.115914+01:00",
  "msg": {
    "best": 63,
    "id": 11
  }
}
{
  "time": "2019-02-05T18:10:08.304876+01:00",
  "msg": {
    "id": 6,
    "best": 63
  }
}
{
  "msg": {
    "id": 10,
    "best": 63
  },
  "time": "2019-02-05T18:10:08.521953+01:00"
}
{
  "msg": {
    "id": 12,
    "best": 63
  },
  "time": "2019-02-05T18:10:08.599115+01:00"
}
{
  "msg": {
    "best": 63,
    "id": 4
  },
  "time": "2019-02-05T18:10:08.674437+01:00"
}
{
  "time": "2019-02-05T18:10:08.944995+01:00",
  "msg": {
    "id": 7,
    "best": 63
  }
}
{
  "msg": {
    "best": 63,
    "id": 11
  },
  "time": "2019-02-05T18:10:08.953665+01:00"
}
{
  "time": "2019-02-05T18:10:09.071063+01:00",
  "msg": {
    "id": 6,
    "best": 63
  }
}
{
  "time": "2019-02-05T18:10:09.760611+01:00",
  "msg": {
    "id": 11,
    "best": 63
  }
}
{
  "msg": {
    "best": 62,
    "id": 10
  },
  "time": "2019-02-05T18:10:10.000801+01:00"
}
{
  "msg": {
    "best": 62,
    "id": 9
  },
  "time": "2019-02-05T18:10:10.581627+01:00"
}
{
  "time": "2019-02-05T18:10:11.332037+01:00",
  "msg": {
    "best": 63,
    "id": 9
  }
}
{
  "time": "2019-02-05T18:10:11.932166+01:00",
  "msg": {
    "best": 63,
    "id": 12
  }
}
{
  "time": "2019-02-05T18:10:12.774096+01:00",
  "msg": {
    "id": 12,
    "best": 63
  }
}
{
  "msg": {
    "id": 12,
    "best": 63
  },
  "time": "2019-02-05T18:10:13.565428+01:00"
}
{
  "time": "2019-02-05T18:10:14.186191+01:00",
  "msg": {
    "id": 8,
    "best": 63
  }
}
{
  "time": "2019-02-05T18:10:14.523420+01:00",
  "msg": {
    "best": 63,
    "id": 12
  }
}
{
  "time": "2019-02-05T18:10:15.049227+01:00",
  "msg": {
    "id": 8,
    "best": 63
  }
}
{
  "msg": {
    "best": 63,
    "id": 12
  },
  "time": "2019-02-05T18:10:15.339745+01:00"
}
{
  "time": "2019-02-05T18:10:15.921288+01:00",
  "msg": {
    "best": 63,
    "id": 8
  }
}
{
  "time": "2019-02-05T18:10:16.703644+01:00",
  "msg": {
    "id": 8,
    "best": 63
  }
}
{
  "msg": {
    "id": 8,
    "best": 63
  },
  "time": "2019-02-05T18:10:17.423373+01:00"
}
{
  "msg": {
    "best": 63,
    "id": 4
  },
  "time": "2019-02-05T18:10:19.887610+01:00"
}
{
  "msg": {
    "best": 63,
    "id": 7
  },
  "time": "2019-02-05T18:10:20.233899+01:00"
}
{
  "msg": {
    "id": 6,
    "best": 63
  },
  "time": "2019-02-05T18:10:20.547489+01:00"
}
{
  "time": "2019-02-05T18:10:20.783561+01:00",
  "msg": {
    "id": 4,
    "best": 63
  }
}
{
  "msg": {
    "id": 10,
    "best": 63
  },
  "time": "2019-02-05T18:10:20.995303+01:00"
}
{
  "time": "2019-02-05T18:10:21.270619+01:00",
  "msg": {
    "best": 63,
    "id": 11
  }
}
{
  "msg": {
    "id": 9,
    "best": 63
  },
  "time": "2019-02-05T18:10:22.630136+01:00"
}
{
  "time": "2019-02-05T18:10:25.947727+01:00",
  "msg": {
    "best": 63,
    "id": 12
  }
}
{
  "msg": {
    "best": 63,
    "id": 8
  },
  "time": "2019-02-05T18:10:28.245066+01:00"
}
{
  "msg": {
    "best": 63,
    "id": 12
  },
  "time": "2019-02-05T18:10:30.240242+01:00"
}
{
  "time": "2019-02-05T18:10:30.673201+01:00",
  "msg": {
    "best": 63,
    "id": 6
  }
}
{
  "time": "2019-02-05T18:10:30.858831+01:00",
  "msg": {
    "id": 7,
    "best": 63
  }
}
{
  "time": "2019-02-05T18:10:30.980195+01:00",
  "msg": {
    "id": 4,
    "best": 63
  }
}
{
  "msg": {
    "id": 12,
    "best": 63
  },
  "time": "2019-02-05T18:10:31.098391+01:00"
}
{
  "time": "2019-02-05T18:10:31.467492+01:00",
  "msg": {
    "best": 63,
    "id": 10
  }
}
{
  "time": "2019-02-05T18:10:31.503419+01:00",
  "msg": {
    "best": 63,
    "id": 6
  }
}
{
  "msg": {
    "id": 11,
    "best": 63
  },
  "time": "2019-02-05T18:10:31.714626+01:00"
}
{
  "msg": {
    "best": 63,
    "id": 7
  },
  "time": "2019-02-05T18:10:31.717055+01:00"
}
{
  "time": "2019-02-05T18:10:33.239857+01:00",
  "msg": {
    "best": 63,
    "id": 9
  }
}
{
  "msg": {
    "id": 9,
    "best": 63
  },
  "time": "2019-02-05T18:10:33.997962+01:00"
}
{
  "msg": {
    "best": 62,
    "id": 9
  },
  "time": "2019-02-05T18:10:34.736810+01:00"
}
{
  "msg": {
    "id": 8,
    "best": 63
  },
  "time": "2019-02-05T18:10:38.613724+01:00"
}
{
  "time": "2019-02-05T18:10:39.285899+01:00",
  "msg": {
    "id": 8,
    "best": 62
  }
}
{
  "time": "2019-02-05T18:10:41.627765+01:00",
  "msg": {
    "best": 63,
    "id": 4
  }
}
{
  "msg": {
    "id": 10,
    "best": 63
  },
  "time": "2019-02-05T18:10:41.828442+01:00"
}
{
  "time": "2019-02-05T18:10:41.874380+01:00",
  "msg": {
    "id": 12,
    "best": 63
  }
}
{
  "time": "2019-02-05T18:10:42.108671+01:00",
  "msg": {
    "best": 63,
    "id": 6
  }
}
{
  "msg": {
    "best": 63,
    "id": 11
  },
  "time": "2019-02-05T18:10:42.235435+01:00"
}
{
  "msg": {
    "id": 4,
    "best": 63
  },
  "time": "2019-02-05T18:10:42.397740+01:00"
}
{
  "time": "2019-02-05T18:10:42.592114+01:00",
  "msg": {
    "id": 7,
    "best": 63
  }
}
{
  "time": "2019-02-05T18:10:42.889374+01:00",
  "msg": {
    "best": 63,
    "id": 6
  }
}
{
  "time": "2019-02-05T18:10:43.186680+01:00",
  "msg": {
    "id": 4,
    "best": 63
  }
}
{
  "msg": {
    "id": 7,
    "best": 62
  },
  "time": "2019-02-05T18:10:43.323312+01:00"
}
{
  "msg": {
    "id": 6,
    "best": 63
  },
  "time": "2019-02-05T18:10:43.674347+01:00"
}
{
  "time": "2019-02-05T18:10:43.949970+01:00",
  "msg": {
    "id": 4,
    "best": 63
  }
}
{
  "time": "2019-02-05T18:10:44.372102+01:00",
  "msg": {
    "id": 6,
    "best": 63
  }
}
{
  "msg": {
    "id": 4,
    "best": 63
  },
  "time": "2019-02-05T18:10:44.695673+01:00"
}
{
  "time": "2019-02-05T18:10:45.058666+01:00",
  "msg": {
    "id": 6,
    "best": 63
  }
}
{
  "time": "2019-02-05T18:10:45.369205+01:00",
  "msg": {
    "id": 9,
    "best": 62
  }
}
{
  "msg": {
    "id": 4,
    "best": 63
  },
  "time": "2019-02-05T18:10:45.461098+01:00"
}
{
  "time": "2019-02-05T18:10:46.074108+01:00",
  "msg": {
    "id": 9,
    "best": 63
  }
}
{
  "msg": {
    "best": 63,
    "id": 4
  },
  "time": "2019-02-05T18:10:46.312037+01:00"
}
{
  "time": "2019-02-05T18:10:46.867998+01:00",
  "msg": {
    "best": 63,
    "id": 9
  }
}
{
  "time": "2019-02-05T18:10:47.123194+01:00",
  "msg": {
    "best": 63,
    "id": 4
  }
}
{
  "time": "2019-02-05T18:10:47.674369+01:00",
  "msg": {
    "best": 63,
    "id": 9
  }
}
{
  "msg": {
    "id": 4,
    "best": 63
  },
  "time": "2019-02-05T18:10:47.897019+01:00"
}
{
  "time": "2019-02-05T18:10:48.731942+01:00",
  "msg": {
    "id": 9,
    "best": 63
  }
}
{
  "msg": {
    "best": 62,
    "id": 4
  },
  "time": "2019-02-05T18:10:48.981573+01:00"
}
{
  "msg": {
    "id": 9,
    "best": 63
  },
  "time": "2019-02-05T18:10:49.563852+01:00"
}
{
  "msg": {
    "id": 4,
    "best": 63
  },
  "time": "2019-02-05T18:10:49.835694+01:00"
}
{
  "msg": {
    "id": 9,
    "best": 62
  },
  "time": "2019-02-05T18:10:50.388370+01:00"
}
{
  "time": "2019-02-05T18:10:50.656906+01:00",
  "msg": {
    "best": 63,
    "id": 4
  }
}
{
  "msg": {
    "id": 8,
    "best": 62
  },
  "time": "2019-02-05T18:10:51.019917+01:00"
}
{
  "msg": {
    "id": 9,
    "best": 63
  },
  "time": "2019-02-05T18:10:51.191927+01:00"
}
{
  "time": "2019-02-05T18:10:51.809220+01:00",
  "msg": {
    "id": 8,
    "best": 63
  }
}
{
  "time": "2019-02-05T18:10:53.182131+01:00",
  "msg": {
    "id": 10,
    "best": 63
  }
}
{
  "msg": {
    "id": 12,
    "best": 63
  },
  "time": "2019-02-05T18:10:53.497111+01:00"
}
{
  "msg": {
    "best": 63,
    "id": 11
  },
  "time": "2019-02-05T18:10:53.999994+01:00"
}
{
  "msg": {
    "id": 7,
    "best": 62
  },
  "time": "2019-02-05T18:10:54.845140+01:00"
}
{
  "time": "2019-02-05T18:10:55.696104+01:00",
  "msg": {
    "id": 7,
    "best": 62
  }
}
{
  "time": "2019-02-05T18:10:56.437322+01:00",
  "msg": {
    "best": 63,
    "id": 7
  }
}
{
  "time": "2019-02-05T18:10:56.450804+01:00",
  "msg": {
    "id": 6,
    "best": 63
  }
}
{
  "msg": {
    "best": 63,
    "id": 7
  },
  "time": "2019-02-05T18:10:57.540290+01:00"
}
{
  "msg": {
    "id": 7,
    "best": 63
  },
  "time": "2019-02-05T18:10:58.397470+01:00"
}
{
  "msg": {
    "id": 7,
    "best": 63
  },
  "time": "2019-02-05T18:10:59.214033+01:00"
}
{
  "msg": {
    "id": 7,
    "best": 63
  },
  "time": "2019-02-05T18:10:59.846151+01:00"
}
{
  "msg": {
    "id": 7,
    "best": 63
  },
  "time": "2019-02-05T18:11:00.630076+01:00"
}
{
  "msg": {
    "id": 4,
    "best": 63
  },
  "time": "2019-02-05T18:11:01.944257+01:00"
}
{
  "msg": {
    "best": 63,
    "id": 9
  },
  "time": "2019-02-05T18:11:02.603390+01:00"
}
{
  "time": "2019-02-05T18:11:03.389539+01:00",
  "msg": {
    "best": 63,
    "id": 8
  }
}
{
  "time": "2019-02-05T18:11:04.726121+01:00",
  "msg": {
    "best": 63,
    "id": 10
  }
}
{
  "time": "2019-02-05T18:11:04.956959+01:00",
  "msg": {
    "id": 12,
    "best": 63
  }
}
{
  "time": "2019-02-05T18:11:05.573496+01:00",
  "msg": {
    "id": 11,
    "best": 63
  }
}
{
  "msg": {
    "id": 12,
    "best": 63
  },
  "time": "2019-02-05T18:11:05.859076+01:00"
}
{
  "msg": {
    "best": 62,
    "id": 6
  },
  "time": "2019-02-05T18:11:08.273051+01:00"
}
{
  "msg": {
    "id": 7,
    "best": 63
  },
  "time": "2019-02-05T18:11:09.519605+01:00"
}
{
  "time": "2019-02-05T18:11:13.229496+01:00",
  "msg": {
    "id": 4,
    "best": 63
  }
}
{
  "time": "2019-02-05T18:11:13.941755+01:00",
  "msg": {
    "best": 63,
    "id": 9
  }
}
{
  "msg": {
    "best": 62,
    "id": 4
  },
  "time": "2019-02-05T18:11:14.195122+01:00"
}
{
  "time": "2019-02-05T18:11:14.854659+01:00",
  "msg": {
    "id": 9,
    "best": 62
  }
}
{
  "time": "2019-02-05T18:11:15.045548+01:00",
  "msg": {
    "id": 4,
    "best": 62
  }
}
{
  "time": "2019-02-05T18:11:15.310440+01:00",
  "msg": {
    "id": 8,
    "best": 63
  }
}
{
  "time": "2019-02-05T18:11:16.278504+01:00",
  "msg": {
    "id": 10,
    "best": 62
  }
}
{
  "msg": {
    "best": 63,
    "id": 11
  },
  "time": "2019-02-05T18:11:17.422572+01:00"
}
{
  "msg": {
    "id": 12,
    "best": 63
  },
  "time": "2019-02-05T18:11:17.801032+01:00"
}
{
  "msg": {
    "id": 6,
    "best": 63
  },
  "time": "2019-02-05T18:11:19.658772+01:00"
}
{
  "time": "2019-02-05T18:11:20.701437+01:00",
  "msg": {
    "id": 7,
    "best": 63
  }
}
{
  "msg": {
    "id": 7,
    "best": 63
  },
  "time": "2019-02-05T18:11:21.476757+01:00"
}
{
  "msg": {
    "id": 9,
    "best": 63
  },
  "time": "2019-02-05T18:11:25.950954+01:00"
}
{
  "time": "2019-02-05T18:11:26.203151+01:00",
  "msg": {
    "best": 63,
    "id": 4
  }
}
{
  "msg": {
    "best": 62,
    "id": 8
  },
  "time": "2019-02-05T18:11:26.939269+01:00"
}
{
  "msg": {
    "best": 63,
    "id": 10
  },
  "time": "2019-02-05T18:11:27.593710+01:00"
}
{
  "msg": {
    "best": 63,
    "id": 8
  },
  "time": "2019-02-05T18:11:27.954461+01:00"
}
{
  "time": "2019-02-05T18:11:28.691495+01:00",
  "msg": {
    "id": 11,
    "best": 63
  }
}
{
  "time": "2019-02-05T18:11:28.960302+01:00",
  "msg": {
    "best": 63,
    "id": 12
  }
}
{
  "time": "2019-02-05T18:11:30.911297+01:00",
  "msg": {
    "id": 6,
    "best": 63
  }
}
{
  "time": "2019-02-05T18:11:32.838720+01:00",
  "msg": {
    "best": 63,
    "id": 7
  }
}
{
  "time": "2019-02-05T18:11:33.373149+01:00",
  "msg": {
    "id": 10,
    "best": 62
  }
}
{
  "time": "2019-02-05T18:11:34.258161+01:00",
  "msg": {
    "id": 10,
    "best": 63
  }
}
{
  "msg": {
    "best": 63,
    "id": 10
  },
  "time": "2019-02-05T18:11:35.034269+01:00"
}
{
  "time": "2019-02-05T18:11:37.593311+01:00",
  "msg": {
    "id": 9,
    "best": 62
  }
}
{
  "msg": {
    "id": 4,
    "best": 63
  },
  "time": "2019-02-05T18:11:37.783813+01:00"
}
{
  "msg": {
    "best": 63,
    "id": 9
  },
  "time": "2019-02-05T18:11:38.395007+01:00"
}
{
  "msg": {
    "id": 4,
    "best": 63
  },
  "time": "2019-02-05T18:11:38.586784+01:00"
}
{
  "time": "2019-02-05T18:11:39.174822+01:00",
  "msg": {
    "best": 63,
    "id": 10
  }
}
{
  "time": "2019-02-05T18:11:39.352400+01:00",
  "msg": {
    "best": 63,
    "id": 9
  }
}
{
  "msg": {
    "best": 62,
    "id": 8
  },
  "time": "2019-02-05T18:11:39.567932+01:00"
}
{
  "time": "2019-02-05T18:11:40.104440+01:00",
  "msg": {
    "id": 11,
    "best": 63
  }
}
{
  "msg": {
    "best": 63,
    "id": 12
  },
  "time": "2019-02-05T18:11:40.245415+01:00"
}
{
  "time": "2019-02-05T18:11:40.432371+01:00",
  "msg": {
    "best": 63,
    "id": 8
  }
}
{
  "time": "2019-02-05T18:11:41.022038+01:00",
  "msg": {
    "id": 11,
    "best": 63
  }
}
{
  "msg": {
    "id": 12,
    "best": 63
  },
  "time": "2019-02-05T18:11:41.176523+01:00"
}
{
  "time": "2019-02-05T18:11:41.886877+01:00",
  "msg": {
    "id": 12,
    "best": 63
  }
}
{
  "time": "2019-02-05T18:11:42.528478+01:00",
  "msg": {
    "best": 63,
    "id": 6
  }
}
{
  "msg": {
    "best": 63,
    "id": 11
  },
  "time": "2019-02-05T18:11:42.570136+01:00"
}
{
  "time": "2019-02-05T18:11:42.640974+01:00",
  "msg": {
    "best": 63,
    "id": 12
  }
}
{
  "time": "2019-02-05T18:11:43.294019+01:00",
  "msg": {
    "best": 63,
    "id": 6
  }
}
{
  "msg": {
    "id": 12,
    "best": 63
  },
  "time": "2019-02-05T18:11:43.322432+01:00"
}
{
  "time": "2019-02-05T18:11:43.473266+01:00",
  "msg": {
    "id": 11,
    "best": 63
  }
}
{
  "time": "2019-02-05T18:11:44.152240+01:00",
  "msg": {
    "best": 63,
    "id": 6
  }
}
{
  "msg": {
    "id": 12,
    "best": 63
  },
  "time": "2019-02-05T18:11:44.295807+01:00"
}
{
  "msg": {
    "id": 11,
    "best": 63
  },
  "time": "2019-02-05T18:11:44.303996+01:00"
}
{
  "msg": {
    "best": 63,
    "id": 7
  },
  "time": "2019-02-05T18:11:44.687445+01:00"
}
{
  "msg": {
    "id": 6,
    "best": 63
  },
  "time": "2019-02-05T18:11:45.034652+01:00"
}
{
  "time": "2019-02-05T18:11:45.062214+01:00",
  "msg": {
    "best": 63,
    "id": 12
  }
}
{
  "msg": {
    "id": 11,
    "best": 63
  },
  "time": "2019-02-05T18:11:45.117559+01:00"
}
{
  "msg": {
    "best": 63,
    "id": 7
  },
  "time": "2019-02-05T18:11:45.521119+01:00"
}
{
  "time": "2019-02-05T18:11:45.893487+01:00",
  "msg": {
    "best": 63,
    "id": 11
  }
}
{
  "msg": {
    "id": 12,
    "best": 63
  },
  "time": "2019-02-05T18:11:45.944920+01:00"
}
{
  "time": "2019-02-05T18:11:46.380580+01:00",
  "msg": {
    "best": 63,
    "id": 7
  }
}
{
  "msg": {
    "id": 11,
    "best": 63
  },
  "time": "2019-02-05T18:11:46.733917+01:00"
}
{
  "msg": {
    "id": 12,
    "best": 63
  },
  "time": "2019-02-05T18:11:46.866562+01:00"
}
{
  "time": "2019-02-05T18:11:47.238562+01:00",
  "msg": {
    "id": 7,
    "best": 63
  }
}
{
  "time": "2019-02-05T18:11:47.581165+01:00",
  "msg": {
    "best": 63,
    "id": 11
  }
}
{
  "time": "2019-02-05T18:11:47.768940+01:00",
  "msg": {
    "best": 63,
    "id": 12
  }
}
{
  "time": "2019-02-05T18:11:48.165416+01:00",
  "msg": {
    "best": 63,
    "id": 7
  }
}
{
  "msg": {
    "best": 63,
    "id": 12
  },
  "time": "2019-02-05T18:11:48.648083+01:00"
}
{
  "time": "2019-02-05T18:11:48.962622+01:00",
  "msg": {
    "id": 7,
    "best": 63
  }
}
{
  "time": "2019-02-05T18:11:49.236363+01:00",
  "msg": {
    "id": 11,
    "best": 63
  }
}
{
  "time": "2019-02-05T18:11:49.436153+01:00",
  "msg": {
    "id": 12,
    "best": 63
  }
}
{
  "time": "2019-02-05T18:11:50.048120+01:00",
  "msg": {
    "best": 63,
    "id": 11
  }
}
{
  "time": "2019-02-05T18:11:50.928234+01:00",
  "msg": {
    "best": 63,
    "id": 11
  }
}
{
  "msg": {
    "best": 63,
    "id": 4
  },
  "time": "2019-02-05T18:11:51.126750+01:00"
}
{
  "time": "2019-02-05T18:11:51.644942+01:00",
  "msg": {
    "id": 7,
    "best": 63
  }
}
{
  "msg": {
    "best": 63,
    "id": 10
  },
  "time": "2019-02-05T18:11:52.078048+01:00"
}
{
  "msg": {
    "best": 63,
    "id": 11
  },
  "time": "2019-02-05T18:11:52.260728+01:00"
}
{
  "msg": {
    "id": 4,
    "best": 63
  },
  "time": "2019-02-05T18:11:52.384360+01:00"
}
{
  "time": "2019-02-05T18:11:52.540484+01:00",
  "msg": {
    "best": 63,
    "id": 9
  }
}
{
  "msg": {
    "id": 7,
    "best": 63
  },
  "time": "2019-02-05T18:11:52.668852+01:00"
}
{
  "msg": {
    "best": 63,
    "id": 10
  },
  "time": "2019-02-05T18:11:53.069751+01:00"
}
{
  "time": "2019-02-05T18:11:53.178661+01:00",
  "msg": {
    "id": 11,
    "best": 63
  }
}
{
  "time": "2019-02-05T18:11:53.261966+01:00",
  "msg": {
    "id": 8,
    "best": 63
  }
}
{
  "time": "2019-02-05T18:11:53.455125+01:00",
  "msg": {
    "id": 9,
    "best": 63
  }
}
{
  "time": "2019-02-05T18:11:53.910546+01:00",
  "msg": {
    "best": 63,
    "id": 10
  }
}
{
  "msg": {
    "best": 62,
    "id": 11
  },
  "time": "2019-02-05T18:11:54.099686+01:00"
}
{
  "msg": {
    "best": 62,
    "id": 8
  },
  "time": "2019-02-05T18:11:54.210546+01:00"
}
{
  "time": "2019-02-05T18:11:54.488725+01:00",
  "msg": {
    "best": 63,
    "id": 9
  }
}
{
  "msg": {
    "best": 63,
    "id": 10
  },
  "time": "2019-02-05T18:11:54.857294+01:00"
}
{
  "msg": {
    "id": 11,
    "best": 62
  },
  "time": "2019-02-05T18:11:55.134185+01:00"
}
{
  "time": "2019-02-05T18:11:55.267603+01:00",
  "msg": {
    "best": 63,
    "id": 8
  }
}
{
  "time": "2019-02-05T18:11:55.467233+01:00",
  "msg": {
    "best": 63,
    "id": 9
  }
}
{
  "msg": {
    "id": 10,
    "best": 62
  },
  "time": "2019-02-05T18:11:55.828976+01:00"
}
{
  "msg": {
    "id": 8,
    "best": 63
  },
  "time": "2019-02-05T18:11:56.267937+01:00"
}
{
  "msg": {
    "best": 62,
    "id": 11
  },
  "time": "2019-02-05T18:11:56.804153+01:00"
}
{
  "time": "2019-02-05T18:11:56.805389+01:00",
  "msg": {
    "id": 10,
    "best": 62
  }
}
{
  "time": "2019-02-05T18:11:57.323572+01:00",
  "msg": {
    "best": 62,
    "id": 8
  }
}
{
  "time": "2019-02-05T18:11:57.770995+01:00",
  "msg": {
    "best": 63,
    "id": 10
  }
}
{
  "time": "2019-02-05T18:11:57.954914+01:00",
  "msg": {
    "id": 11,
    "best": 63
  }
}
{
  "time": "2019-02-05T18:11:58.166820+01:00",
  "msg": {
    "best": 62,
    "id": 6
  }
}
{
  "msg": {
    "id": 8,
    "best": 62
  },
  "time": "2019-02-05T18:11:58.297279+01:00"
}
{
  "msg": {
    "best": 63,
    "id": 10
  },
  "time": "2019-02-05T18:11:58.685643+01:00"
}
{
  "time": "2019-02-05T18:11:59.053784+01:00",
  "msg": {
    "best": 62,
    "id": 6
  }
}
{
  "msg": {
    "id": 10,
    "best": 62
  },
  "time": "2019-02-05T18:11:59.681859+01:00"
}
{
  "time": "2019-02-05T18:12:00.031534+01:00",
  "msg": {
    "id": 6,
    "best": 63
  }
}
{
  "msg": {
    "id": 10,
    "best": 63
  },
  "time": "2019-02-05T18:12:00.615689+01:00"
}
{
  "time": "2019-02-05T18:12:00.906623+01:00",
  "msg": {
    "id": 6,
    "best": 63
  }
}
{
  "time": "2019-02-05T18:12:01.622903+01:00",
  "msg": {
    "best": 63,
    "id": 6
  }
}
{
  "time": "2019-02-05T18:12:02.725873+01:00",
  "msg": {
    "best": 63,
    "id": 8
  }
}
{
  "time": "2019-02-05T18:12:02.955349+01:00",
  "msg": {
    "best": 63,
    "id": 12
  }
}
{
  "msg": {
    "best": 63,
    "id": 8
  },
  "time": "2019-02-05T18:12:03.654209+01:00"
}
{
  "time": "2019-02-05T18:12:03.785362+01:00",
  "msg": {
    "id": 12,
    "best": 63
  }
}
{
  "time": "2019-02-05T18:12:04.538556+01:00",
  "msg": {
    "best": 62,
    "id": 12
  }
}
{
  "msg": {
    "best": 62,
    "id": 12
  },
  "time": "2019-02-05T18:12:05.301423+01:00"
}
{
  "msg": {
    "id": 4,
    "best": 62
  },
  "time": "2019-02-05T18:12:05.424158+01:00"
}
{
  "msg": {
    "best": 63,
    "id": 7
  },
  "time": "2019-02-05T18:12:05.715860+01:00"
}
{
  "msg": {
    "best": 62,
    "id": 12
  },
  "time": "2019-02-05T18:12:06.178889+01:00"
}
{
  "msg": {
    "id": 7,
    "best": 63
  },
  "time": "2019-02-05T18:12:06.645281+01:00"
}
{
  "msg": {
    "best": 63,
    "id": 9
  },
  "time": "2019-02-05T18:12:08.378989+01:00"
}
{
  "time": "2019-02-05T18:12:10.389410+01:00",
  "msg": {
    "id": 11,
    "best": 63
  }
}
{
  "msg": {
    "best": 62,
    "id": 4
  },
  "time": "2019-02-05T18:12:12.574291+01:00"
}
{
  "time": "2019-02-05T18:12:12.799013+01:00",
  "msg": {
    "id": 10,
    "best": 62
  }
}
{
  "msg": {
    "best": 63,
    "id": 4
  },
  "time": "2019-02-05T18:12:13.519331+01:00"
}
{
  "time": "2019-02-05T18:12:13.665525+01:00",
  "msg": {
    "id": 6,
    "best": 63
  }
}
{
  "time": "2019-02-05T18:12:14.324671+01:00",
  "msg": {
    "id": 4,
    "best": 63
  }
}
{
  "time": "2019-02-05T18:12:16.056032+01:00",
  "msg": {
    "best": 62,
    "id": 8
  }
}
{
  "time": "2019-02-05T18:12:18.192397+01:00",
  "msg": {
    "best": 63,
    "id": 12
  }
}
{
  "msg": {
    "id": 7,
    "best": 63
  },
  "time": "2019-02-05T18:12:18.638725+01:00"
}
{
  "msg": {
    "best": 63,
    "id": 9
  },
  "time": "2019-02-05T18:12:19.720789+01:00"
}
{
  "msg": {
    "best": 63,
    "id": 9
  },
  "time": "2019-02-05T18:12:20.527339+01:00"
}
{
  "msg": {
    "best": 63,
    "id": 9
  },
  "time": "2019-02-05T18:12:21.806700+01:00"
}
{
  "msg": {
    "id": 9,
    "best": 63
  },
  "time": "2019-02-05T18:12:22.544852+01:00"
}
{
  "time": "2019-02-05T18:12:22.757711+01:00",
  "msg": {
    "best": 63,
    "id": 11
  }
}
{
  "time": "2019-02-05T18:12:23.401465+01:00",
  "msg": {
    "id": 9,
    "best": 63
  }
}
{
  "time": "2019-02-05T18:12:23.597576+01:00",
  "msg": {
    "best": 63,
    "id": 11
  }
}
{
  "msg": {
    "id": 11,
    "best": 63
  },
  "time": "2019-02-05T18:12:24.310508+01:00"
}
{
  "time": "2019-02-05T18:12:25.010968+01:00",
  "msg": {
    "id": 9,
    "best": 63
  }
}
{
  "msg": {
    "best": 63,
    "id": 10
  },
  "time": "2019-02-05T18:12:25.054932+01:00"
}
{
  "time": "2019-02-05T18:12:25.246310+01:00",
  "msg": {
    "id": 11,
    "best": 63
  }
}
{
  "time": "2019-02-05T18:12:25.863178+01:00",
  "msg": {
    "best": 63,
    "id": 9
  }
}
{
  "time": "2019-02-05T18:12:26.053606+01:00",
  "msg": {
    "id": 10,
    "best": 63
  }
}
{
  "msg": {
    "id": 11,
    "best": 63
  },
  "time": "2019-02-05T18:12:26.058538+01:00"
}
{
  "time": "2019-02-05T18:12:26.271837+01:00",
  "msg": {
    "best": 63,
    "id": 6
  }
}
{
  "time": "2019-02-05T18:12:26.847195+01:00",
  "msg": {
    "best": 63,
    "id": 9
  }
}
{
  "msg": {
    "best": 63,
    "id": 4
  },
  "time": "2019-02-05T18:12:26.855152+01:00"
}
{
  "msg": {
    "id": 11,
    "best": 63
  },
  "time": "2019-02-05T18:12:27.060948+01:00"
}
{
  "msg": {
    "id": 8,
    "best": 63
  },
  "time": "2019-02-05T18:12:28.712750+01:00"
}
{
  "time": "2019-02-05T18:12:30.871723+01:00",
  "msg": {
    "best": 63,
    "id": 12
  }
}
{
  "msg": {
    "id": 7,
    "best": 63
  },
  "time": "2019-02-05T18:12:31.100724+01:00"
}
{
  "msg": {
    "best": 63,
    "id": 10
  },
  "time": "2019-02-05T18:12:32.165402+01:00"
}
{
  "msg": {
    "best": 63,
    "id": 10
  },
  "time": "2019-02-05T18:12:32.956762+01:00"
}
{
  "time": "2019-02-05T18:12:33.809636+01:00",
  "msg": {
    "id": 10,
    "best": 63
  }
}
{
  "time": "2019-02-05T18:12:34.620528+01:00",
  "msg": {
    "id": 10,
    "best": 63
  }
}
{
  "msg": {
    "id": 10,
    "best": 63
  },
  "time": "2019-02-05T18:12:35.452120+01:00"
}
{
  "time": "2019-02-05T18:12:36.334564+01:00",
  "msg": {
    "best": 63,
    "id": 10
  }
}
{
  "msg": {
    "best": 63,
    "id": 4
  },
  "time": "2019-02-05T18:12:37.166156+01:00"
}
{
  "time": "2019-02-05T18:12:37.615373+01:00",
  "msg": {
    "id": 10,
    "best": 63
  }
}
{
  "msg": {
    "id": 6,
    "best": 63
  },
  "time": "2019-02-05T18:12:38.257922+01:00"
}
{
  "time": "2019-02-05T18:12:38.537072+01:00",
  "msg": {
    "id": 10,
    "best": 63
  }
}
{
  "msg": {
    "id": 9,
    "best": 63
  },
  "time": "2019-02-05T18:12:39.164873+01:00"
}
{
  "msg": {
    "best": 63,
    "id": 11
  },
  "time": "2019-02-05T18:12:39.584711+01:00"
}
{
  "time": "2019-02-05T18:12:39.948844+01:00",
  "msg": {
    "id": 6,
    "best": 63
  }
}
{
  "msg": {
    "id": 8,
    "best": 62
  },
  "time": "2019-02-05T18:12:40.946470+01:00"
}
{
  "msg": {
    "best": 63,
    "id": 12
  },
  "time": "2019-02-05T18:12:43.025669+01:00"
}
{
  "msg": {
    "best": 63,
    "id": 7
  },
  "time": "2019-02-05T18:12:43.453018+01:00"
}
{
  "time": "2019-02-05T18:12:46.431292+01:00",
  "msg": {
    "id": 8,
    "best": 62
  }
}
{
  "msg": {
    "id": 8,
    "best": 63
  },
  "time": "2019-02-05T18:12:47.266642+01:00"
}
{
  "time": "2019-02-05T18:12:48.842391+01:00",
  "msg": {
    "best": 63,
    "id": 4
  }
}
{
  "time": "2019-02-05T18:12:49.942705+01:00",
  "msg": {
    "best": 63,
    "id": 10
  }
}
{
  "msg": {
    "best": 63,
    "id": 9
  },
  "time": "2019-02-05T18:12:50.494832+01:00"
}
{
  "time": "2019-02-05T18:12:51.080883+01:00",
  "msg": {
    "best": 63,
    "id": 11
  }
}
{
  "time": "2019-02-05T18:12:51.390545+01:00",
  "msg": {
    "id": 6,
    "best": 63
  }
}
{
  "time": "2019-02-05T18:12:51.920290+01:00",
  "msg": {
    "best": 63,
    "id": 11
  }
}
{
  "msg": {
    "best": 63,
    "id": 6
  },
  "time": "2019-02-05T18:12:52.208200+01:00"
}
{
  "msg": {
    "best": 63,
    "id": 11
  },
  "time": "2019-02-05T18:12:53.272414+01:00"
}
{
  "time": "2019-02-05T18:12:53.508977+01:00",
  "msg": {
    "id": 8,
    "best": 63
  }
}
{
  "time": "2019-02-05T18:12:54.267979+01:00",
  "msg": {
    "best": 63,
    "id": 8
  }
}
{
  "msg": {
    "best": 63,
    "id": 8
  },
  "time": "2019-02-05T18:12:55.088059+01:00"
}
{
  "msg": {
    "best": 63,
    "id": 12
  },
  "time": "2019-02-05T18:12:55.534342+01:00"
}
{
  "time": "2019-02-05T18:12:55.774433+01:00",
  "msg": {
    "id": 7,
    "best": 63
  }
}
{
  "time": "2019-02-05T18:12:56.046683+01:00",
  "msg": {
    "id": 8,
    "best": 63
  }
}
{
  "time": "2019-02-05T18:12:56.352465+01:00",
  "msg": {
    "best": 63,
    "id": 12
  }
}
{
  "time": "2019-02-05T18:12:56.572191+01:00",
  "msg": {
    "id": 7,
    "best": 63
  }
}
{
  "msg": {
    "id": 8,
    "best": 63
  },
  "time": "2019-02-05T18:12:56.753219+01:00"
}
{
  "msg": {
    "id": 7,
    "best": 63
  },
  "time": "2019-02-05T18:12:57.408277+01:00"
}
{
  "time": "2019-02-05T18:13:00.341744+01:00",
  "msg": {
    "id": 6,
    "best": 63
  }
}
{
  "msg": {
    "id": 6,
    "best": 63
  },
  "time": "2019-02-05T18:13:01.262894+01:00"
}
{
  "msg": {
    "id": 4,
    "best": 63
  },
  "time": "2019-02-05T18:13:01.561734+01:00"
}
{
  "time": "2019-02-05T18:13:02.048415+01:00",
  "msg": {
    "best": 63,
    "id": 6
  }
}
{
  "time": "2019-02-05T18:13:02.312110+01:00",
  "msg": {
    "best": 63,
    "id": 4
  }
}
{
  "msg": {
    "best": 63,
    "id": 10
  },
  "time": "2019-02-05T18:13:02.428911+01:00"
}
{
  "time": "2019-02-05T18:13:02.795358+01:00",
  "msg": {
    "id": 9,
    "best": 63
  }
}
{
  "msg": {
    "id": 6,
    "best": 63
  },
  "time": "2019-02-05T18:13:03.559959+01:00"
}
{
  "msg": {
    "best": 62,
    "id": 4
  },
  "time": "2019-02-05T18:13:03.821035+01:00"
}
{
  "msg": {
    "id": 11,
    "best": 63
  },
  "time": "2019-02-05T18:13:05.084109+01:00"
}
{
  "time": "2019-02-05T18:13:05.340280+01:00",
  "msg": {
    "id": 12,
    "best": 63
  }
}
{
  "time": "2019-02-05T18:13:05.873390+01:00",
  "msg": {
    "id": 11,
    "best": 63
  }
}
{
  "time": "2019-02-05T18:13:06.173043+01:00",
  "msg": {
    "best": 63,
    "id": 12
  }
}
{
  "msg": {
    "best": 63,
    "id": 11
  },
  "time": "2019-02-05T18:13:06.604717+01:00"
}
{
  "msg": {
    "id": 12,
    "best": 62
  },
  "time": "2019-02-05T18:13:06.889167+01:00"
}
{
  "time": "2019-02-05T18:13:07.347355+01:00",
  "msg": {
    "best": 63,
    "id": 4
  }
}
{
  "time": "2019-02-05T18:13:07.488207+01:00",
  "msg": {
    "best": 63,
    "id": 11
  }
}
{
  "msg": {
    "id": 12,
    "best": 62
  },
  "time": "2019-02-05T18:13:07.709906+01:00"
}
{
  "msg": {
    "best": 63,
    "id": 4
  },
  "time": "2019-02-05T18:13:08.185210+01:00"
}
{
  "msg": {
    "best": 63,
    "id": 11
  },
  "time": "2019-02-05T18:13:08.182216+01:00"
}
{
  "msg": {
    "best": 63,
    "id": 12
  },
  "time": "2019-02-05T18:13:08.577333+01:00"
}
{
  "time": "2019-02-05T18:13:08.802137+01:00",
  "msg": {
    "id": 8,
    "best": 63
  }
}
{
  "msg": {
    "id": 4,
    "best": 62
  },
  "time": "2019-02-05T18:13:09.139342+01:00"
}
{
  "msg": {
    "id": 11,
    "best": 62
  },
  "time": "2019-02-05T18:13:09.227401+01:00"
}
{
  "msg": {
    "id": 7,
    "best": 62
  },
  "time": "2019-02-05T18:13:09.311022+01:00"
}
{
  "msg": {
    "best": 63,
    "id": 8
  },
  "time": "2019-02-05T18:13:11.446818+01:00"
}
{
  "msg": {
    "id": 8,
    "best": 62
  },
  "time": "2019-02-05T18:13:12.405600+01:00"
}
{
  "time": "2019-02-05T18:13:14.631938+01:00",
  "msg": {
    "best": 62,
    "id": 10
  }
}
{
  "time": "2019-02-05T18:13:15.028723+01:00",
  "msg": {
    "id": 9,
    "best": 63
  }
}
{
  "time": "2019-02-05T18:13:16.113666+01:00",
  "msg": {
    "id": 6,
    "best": 62
  }
}
{
  "msg": {
    "id": 12,
    "best": 63
  },
  "time": "2019-02-05T18:13:20.760500+01:00"
}
{
  "time": "2019-02-05T18:13:21.119432+01:00",
  "msg": {
    "best": 63,
    "id": 4
  }
}
{
  "msg": {
    "id": 11,
    "best": 62
  },
  "time": "2019-02-05T18:13:21.292144+01:00"
}
{
  "time": "2019-02-05T18:13:21.540370+01:00",
  "msg": {
    "id": 7,
    "best": 63
  }
}
{
  "msg": {
    "best": 62,
    "id": 4
  },
  "time": "2019-02-05T18:13:22.003015+01:00"
}
{
  "msg": {
    "id": 11,
    "best": 63
  },
  "time": "2019-02-05T18:13:22.974807+01:00"
}
{
  "msg": {
    "id": 8,
    "best": 63
  },
  "time": "2019-02-05T18:13:24.046467+01:00"
}
{
  "time": "2019-02-05T18:13:26.456757+01:00",
  "msg": {
    "id": 10,
    "best": 62
  }
}
{
  "msg": {
    "id": 9,
    "best": 63
  },
  "time": "2019-02-05T18:13:26.936325+01:00"
}
{
  "msg": {
    "best": 62,
    "id": 9
  },
  "time": "2019-02-05T18:13:27.765004+01:00"
}
{
  "msg": {
    "best": 63,
    "id": 6
  },
  "time": "2019-02-05T18:13:28.906432+01:00"
}
{
  "time": "2019-02-05T18:13:30.420994+01:00",
  "msg": {
    "id": 6,
    "best": 62
  }
}
{
  "time": "2019-02-05T18:13:33.388039+01:00",
  "msg": {
    "id": 12,
    "best": 63
  }
}
{
  "time": "2019-02-05T18:13:34.153036+01:00",
  "msg": {
    "best": 63,
    "id": 7
  }
}
{
  "msg": {
    "id": 12,
    "best": 63
  },
  "time": "2019-02-05T18:13:34.430502+01:00"
}
{
  "msg": {
    "id": 4,
    "best": 63
  },
  "time": "2019-02-05T18:13:34.696354+01:00"
}
{
  "time": "2019-02-05T18:13:35.283035+01:00",
  "msg": {
    "id": 12,
    "best": 63
  }
}
{
  "msg": {
    "id": 8,
    "best": 63
  },
  "time": "2019-02-05T18:13:35.429040+01:00"
}
{
  "msg": {
    "id": 11,
    "best": 63
  },
  "time": "2019-02-05T18:13:35.577719+01:00"
}
{
  "msg": {
    "id": 12,
    "best": 63
  },
  "time": "2019-02-05T18:13:36.262384+01:00"
}
{
  "time": "2019-02-05T18:13:36.986870+01:00",
  "msg": {
    "best": 63,
    "id": 8
  }
}
{
  "time": "2019-02-05T18:13:38.538867+01:00",
  "msg": {
    "id": 10,
    "best": 63
  }
}
{
  "msg": {
    "best": 63,
    "id": 7
  },
  "time": "2019-02-05T18:13:38.692574+01:00"
}
{
  "msg": {
    "best": 63,
    "id": 7
  },
  "time": "2019-02-05T18:13:39.493797+01:00"
}
{
  "msg": {
    "id": 7,
    "best": 63
  },
  "time": "2019-02-05T18:13:40.421149+01:00"
}
{
  "msg": {
    "best": 63,
    "id": 9
  },
  "time": "2019-02-05T18:13:40.641738+01:00"
}
{
  "time": "2019-02-05T18:13:41.265647+01:00",
  "msg": {
    "best": 63,
    "id": 7
  }
}
{
  "msg": {
    "id": 9,
    "best": 63
  },
  "time": "2019-02-05T18:13:41.554697+01:00"
}
{
  "msg": {
    "best": 63,
    "id": 12
  },
  "time": "2019-02-05T18:13:41.754481+01:00"
}
{
  "msg": {
    "id": 7,
    "best": 63
  },
  "time": "2019-02-05T18:13:42.274894+01:00"
}
{
  "time": "2019-02-05T18:13:42.688678+01:00",
  "msg": {
    "best": 63,
    "id": 9
  }
}
{
  "time": "2019-02-05T18:13:42.791714+01:00",
  "msg": {
    "best": 63,
    "id": 12
  }
}
{
  "msg": {
    "id": 6,
    "best": 63
  },
  "time": "2019-02-05T18:13:42.792032+01:00"
}
{
  "time": "2019-02-05T18:13:43.347472+01:00",
  "msg": {
    "id": 7,
    "best": 63
  }
}
{
  "time": "2019-02-05T18:13:43.710744+01:00",
  "msg": {
    "id": 9,
    "best": 63
  }
}
{
  "time": "2019-02-05T18:13:43.797661+01:00",
  "msg": {
    "best": 63,
    "id": 6
  }
}
{
  "time": "2019-02-05T18:13:43.902210+01:00",
  "msg": {
    "best": 63,
    "id": 12
  }
}
{
  "msg": {
    "best": 63,
    "id": 6
  },
  "time": "2019-02-05T18:13:44.705262+01:00"
}
{
  "time": "2019-02-05T18:13:47.525294+01:00",
  "msg": {
    "best": 63,
    "id": 4
  }
}
{
  "time": "2019-02-05T18:13:49.203519+01:00",
  "msg": {
    "id": 11,
    "best": 63
  }
}
{
  "msg": {
    "best": 63,
    "id": 8
  },
  "time": "2019-02-05T18:13:50.643132+01:00"
}
{
  "msg": {
    "best": 63,
    "id": 8
  },
  "time": "2019-02-05T18:13:51.374179+01:00"
}
{
  "msg": {
    "best": 63,
    "id": 10
  },
  "time": "2019-02-05T18:13:52.206723+01:00"
}
{
  "msg": {
    "id": 7,
    "best": 63
  },
  "time": "2019-02-05T18:13:56.058422+01:00"
}
{
  "time": "2019-02-05T18:13:56.431588+01:00",
  "msg": {
    "id": 9,
    "best": 63
  }
}
{
  "time": "2019-02-05T18:13:56.796093+01:00",
  "msg": {
    "id": 12,
    "best": 63
  }
}
{
  "time": "2019-02-05T18:13:57.030032+01:00",
  "msg": {
    "id": 7,
    "best": 63
  }
}
{
  "msg": {
    "best": 63,
    "id": 6
  },
  "time": "2019-02-05T18:13:57.516102+01:00"
}
{
  "msg": {
    "id": 12,
    "best": 63
  },
  "time": "2019-02-05T18:13:57.869030+01:00"
}
{
  "msg": {
    "id": 4,
    "best": 63
  },
  "time": "2019-02-05T18:14:00.490627+01:00"
}
{
  "time": "2019-02-05T18:14:01.693271+01:00",
  "msg": {
    "best": 63,
    "id": 11
  }
}
{
  "msg": {
    "best": 63,
    "id": 11
  },
  "time": "2019-02-05T18:14:02.588921+01:00"
}
{
  "msg": {
    "best": 63,
    "id": 8
  },
  "time": "2019-02-05T18:14:04.128379+01:00"
}
{
  "time": "2019-02-05T18:14:04.682625+01:00",
  "msg": {
    "id": 10,
    "best": 63
  }
}
{
  "msg": {
    "id": 10,
    "best": 63
  },
  "time": "2019-02-05T18:14:05.561253+01:00"
}
{
  "msg": {
    "id": 9,
    "best": 63
  },
  "time": "2019-02-05T18:14:08.693655+01:00"
}
{
  "msg": {
    "best": 62,
    "id": 7
  },
  "time": "2019-02-05T18:14:10.231000+01:00"
}
{
  "msg": {
    "id": 6,
    "best": 62
  },
  "time": "2019-02-05T18:14:10.272413+01:00"
}
{
  "time": "2019-02-05T18:14:10.678839+01:00",
  "msg": {
    "best": 63,
    "id": 12
  }
}
{
  "time": "2019-02-05T18:14:11.234461+01:00",
  "msg": {
    "id": 7,
    "best": 63
  }
}
{
  "time": "2019-02-05T18:14:11.692119+01:00",
  "msg": {
    "id": 12,
    "best": 62
  }
}
{
  "time": "2019-02-05T18:14:12.615706+01:00",
  "msg": {
    "id": 12,
    "best": 62
  }
}
{
  "time": "2019-02-05T18:14:13.043079+01:00",
  "msg": {
    "id": 7,
    "best": 63
  }
}
{
  "time": "2019-02-05T18:14:13.841290+01:00",
  "msg": {
    "best": 63,
    "id": 4
  }
}
{
  "msg": {
    "id": 11,
    "best": 63
  },
  "time": "2019-02-05T18:14:15.796012+01:00"
}
{
  "msg": {
    "best": 63,
    "id": 8
  },
  "time": "2019-02-05T18:14:17.280569+01:00"
}
{
  "msg": {
    "id": 8,
    "best": 63
  },
  "time": "2019-02-05T18:14:18.135288+01:00"
}
{
  "msg": {
    "id": 10,
    "best": 63
  },
  "time": "2019-02-05T18:14:18.565225+01:00"
}
{
  "msg": {
    "id": 9,
    "best": 63
  },
  "time": "2019-02-05T18:14:21.770401+01:00"
}
{
  "time": "2019-02-05T18:14:22.558246+01:00",
  "msg": {
    "best": 62,
    "id": 6
  }
}
{
  "time": "2019-02-05T18:14:24.424719+01:00",
  "msg": {
    "id": 12,
    "best": 62
  }
}
{
  "msg": {
    "best": 62,
    "id": 7
  },
  "time": "2019-02-05T18:14:24.960395+01:00"
}
{
  "time": "2019-02-05T18:14:25.242546+01:00",
  "msg": {
    "best": 63,
    "id": 12
  }
}
{
  "time": "2019-02-05T18:14:25.699804+01:00",
  "msg": {
    "best": 61,
    "id": 4
  }
}
{
  "msg": {
    "best": 63,
    "id": 11
  },
  "time": "2019-02-05T18:14:27.275034+01:00"
}
{
  "time": "2019-02-05T18:14:30.134968+01:00",
  "msg": {
    "id": 8,
    "best": 62
  }
}
{
  "msg": {
    "id": 10,
    "best": 62
  },
  "time": "2019-02-05T18:14:30.304849+01:00"
}
{
  "msg": {
    "best": 62,
    "id": 8
  },
  "time": "2019-02-05T18:14:31.732258+01:00"
}
{
  "msg": {
    "id": 10,
    "best": 63
  },
  "time": "2019-02-05T18:14:32.080661+01:00"
}
{
  "time": "2019-02-05T18:14:34.436358+01:00",
  "msg": {
    "best": 63,
    "id": 9
  }
}
{
  "msg": {
    "best": 63,
    "id": 6
  },
  "time": "2019-02-05T18:14:35.138404+01:00"
}
{
  "time": "2019-02-05T18:14:37.551731+01:00",
  "msg": {
    "best": 63,
    "id": 7
  }
}
{
  "time": "2019-02-05T18:14:38.128933+01:00",
  "msg": {
    "best": 63,
    "id": 4
  }
}
{
  "msg": {
    "id": 12,
    "best": 63
  },
  "time": "2019-02-05T18:14:38.328876+01:00"
}
{
  "time": "2019-02-05T18:14:39.184527+01:00",
  "msg": {
    "id": 12,
    "best": 63
  }
}
{
  "time": "2019-02-05T18:14:39.624423+01:00",
  "msg": {
    "id": 7,
    "best": 63
  }
}
{
  "msg": {
    "id": 12,
    "best": 63
  },
  "time": "2019-02-05T18:14:40.276763+01:00"
}
{
  "msg": {
    "best": 63,
    "id": 11
  },
  "time": "2019-02-05T18:14:40.769580+01:00"
}
{
  "msg": {
    "best": 63,
    "id": 12
  },
  "time": "2019-02-05T18:14:41.233953+01:00"
}
{
  "time": "2019-02-05T18:14:41.622372+01:00",
  "msg": {
    "id": 11,
    "best": 63
  }
}
{
  "msg": {
    "best": 63,
    "id": 7
  },
  "time": "2019-02-05T18:14:43.615128+01:00"
}
{
  "msg": {
    "best": 63,
    "id": 8
  },
  "time": "2019-02-05T18:14:44.406649+01:00"
}
{
  "time": "2019-02-05T18:14:44.709949+01:00",
  "msg": {
    "id": 7,
    "best": 63
  }
}
{
  "time": "2019-02-05T18:14:44.840768+01:00",
  "msg": {
    "best": 63,
    "id": 10
  }
}
{
  "time": "2019-02-05T18:14:45.366185+01:00",
  "msg": {
    "id": 8,
    "best": 63
  }
}
{
  "msg": {
    "id": 8,
    "best": 63
  },
  "time": "2019-02-05T18:14:46.413785+01:00"
}
{
  "time": "2019-02-05T18:14:47.778955+01:00",
  "msg": {
    "id": 9,
    "best": 63
  }
}
{
  "time": "2019-02-05T18:14:48.454530+01:00",
  "msg": {
    "id": 6,
    "best": 63
  }
}
{
  "time": "2019-02-05T18:14:51.804000+01:00",
  "msg": {
    "id": 4,
    "best": 63
  }
}
{
  "time": "2019-02-05T18:14:54.201387+01:00",
  "msg": {
    "best": 63,
    "id": 11
  }
}
{
  "time": "2019-02-05T18:14:54.273833+01:00",
  "msg": {
    "best": 63,
    "id": 12
  }
}
{
  "time": "2019-02-05T18:14:57.704617+01:00",
  "msg": {
    "best": 63,
    "id": 7
  }
}
{
  "msg": {
    "best": 62,
    "id": 10
  },
  "time": "2019-02-05T18:14:58.437566+01:00"
}
{
  "msg": {
    "id": 7,
    "best": 62
  },
  "time": "2019-02-05T18:14:58.732456+01:00"
}
{
  "msg": {
    "best": 63,
    "id": 8
  },
  "time": "2019-02-05T18:14:59.704575+01:00"
}
{
  "msg": {
    "id": 9,
    "best": 62
  },
  "time": "2019-02-05T18:15:01.015247+01:00"
}
{
  "msg": {
    "id": 6,
    "best": 63
  },
  "time": "2019-02-05T18:15:01.588998+01:00"
}
{
  "msg": {
    "id": 6,
    "best": 63
  },
  "time": "2019-02-05T18:15:02.590760+01:00"
}
{
  "msg": {
    "best": 63,
    "id": 6
  },
  "time": "2019-02-05T18:15:03.538813+01:00"
}
{
  "msg": {
    "id": 6,
    "best": 62
  },
  "time": "2019-02-05T18:15:04.226422+01:00"
}
{
  "msg": {
    "best": 63,
    "id": 6
  },
  "time": "2019-02-05T18:15:04.916490+01:00"
}
{
  "time": "2019-02-05T18:15:05.096264+01:00",
  "msg": {
    "best": 63,
    "id": 4
  }
}
{
  "time": "2019-02-05T18:15:07.189382+01:00",
  "msg": {
    "best": 62,
    "id": 12
  }
}
{
  "msg": {
    "best": 63,
    "id": 11
  },
  "time": "2019-02-05T18:15:07.752867+01:00"
}
{
  "time": "2019-02-05T18:15:08.944049+01:00",
  "msg": {
    "best": 63,
    "id": 11
  }
}
{
  "msg": {
    "id": 10,
    "best": 62
  },
  "time": "2019-02-05T18:15:12.228945+01:00"
}
{
  "time": "2019-02-05T18:15:12.547563+01:00",
  "msg": {
    "best": 63,
    "id": 7
  }
}
{
  "msg": {
    "id": 10,
    "best": 63
  },
  "time": "2019-02-05T18:15:13.619360+01:00"
}
{
  "time": "2019-02-05T18:15:14.994907+01:00",
  "msg": {
    "best": 63,
    "id": 8
  }
}
{
  "msg": {
    "best": 63,
    "id": 9
  },
  "time": "2019-02-05T18:15:16.120582+01:00"
}
{
  "time": "2019-02-05T18:15:19.828240+01:00",
  "msg": {
    "id": 4,
    "best": 63
  }
}
{
  "msg": {
    "best": 63,
    "id": 6
  },
  "time": "2019-02-05T18:15:20.230248+01:00"
}
{
  "time": "2019-02-05T18:15:21.421789+01:00",
  "msg": {
    "best": 62,
    "id": 6
  }
}
{
  "time": "2019-02-05T18:15:22.569355+01:00",
  "msg": {
    "id": 6,
    "best": 63
  }
}
{
  "time": "2019-02-05T18:15:24.195550+01:00",
  "msg": {
    "id": 12,
    "best": 63
  }
}
{
  "time": "2019-02-05T18:15:25.417265+01:00",
  "msg": {
    "id": 12,
    "best": 63
  }
}
{
  "time": "2019-02-05T18:15:26.230181+01:00",
  "msg": {
    "best": 62,
    "id": 11
  }
}
{
  "msg": {
    "id": 4,
    "best": 62
  },
  "time": "2019-02-05T18:15:26.621060+01:00"
}
{
  "time": "2019-02-05T18:15:26.803860+01:00",
  "msg": {
    "best": 63,
    "id": 12
  }
}
{
  "msg": {
    "best": 62,
    "id": 7
  },
  "time": "2019-02-05T18:15:28.956867+01:00"
}
{
  "msg": {
    "id": 10,
    "best": 63
  },
  "time": "2019-02-05T18:15:29.561269+01:00"
}
{
  "time": "2019-02-05T18:15:30.421860+01:00",
  "msg": {
    "best": 62,
    "id": 10
  }
}
{
  "time": "2019-02-05T18:15:31.077518+01:00",
  "msg": {
    "id": 8,
    "best": 63
  }
}
{
  "msg": {
    "id": 9,
    "best": 62
  },
  "time": "2019-02-05T18:15:31.470012+01:00"
}
{
  "msg": {
    "id": 10,
    "best": 62
  },
  "time": "2019-02-05T18:15:31.556784+01:00"
}
{
  "msg": {
    "id": 8,
    "best": 63
  },
  "time": "2019-02-05T18:15:32.069791+01:00"
}
{
  "msg": {
    "best": 63,
    "id": 9
  },
  "time": "2019-02-05T18:15:32.398182+01:00"
}
{
  "msg": {
    "best": 63,
    "id": 10
  },
  "time": "2019-02-05T18:15:32.528734+01:00"
}
{
  "time": "2019-02-05T18:15:33.023255+01:00",
  "msg": {
    "best": 63,
    "id": 8
  }
}
{
  "time": "2019-02-05T18:15:33.329606+01:00",
  "msg": {
    "id": 9,
    "best": 63
  }
}
{
  "msg": {
    "id": 10,
    "best": 63
  },
  "time": "2019-02-05T18:15:33.419341+01:00"
}
{
  "msg": {
    "best": 63,
    "id": 8
  },
  "time": "2019-02-05T18:15:33.963086+01:00"
}
{
  "msg": {
    "id": 10,
    "best": 63
  },
  "time": "2019-02-05T18:15:34.254685+01:00"
}
{
  "time": "2019-02-05T18:15:34.266217+01:00",
  "msg": {
    "id": 9,
    "best": 63
  }
}
{
  "time": "2019-02-05T18:15:34.922434+01:00",
  "msg": {
    "id": 8,
    "best": 63
  }
}
{
  "time": "2019-02-05T18:15:35.166569+01:00",
  "msg": {
    "id": 10,
    "best": 63
  }
}
{
  "msg": {
    "best": 63,
    "id": 8
  },
  "time": "2019-02-05T18:15:35.796153+01:00"
}
{
  "msg": {
    "id": 8,
    "best": 63
  },
  "time": "2019-02-05T18:15:36.665379+01:00"
}
{
  "msg": {
    "best": 63,
    "id": 6
  },
  "time": "2019-02-05T18:15:37.429424+01:00"
}
{
  "time": "2019-02-05T18:15:39.601310+01:00",
  "msg": {
    "best": 63,
    "id": 11
  }
}
{
  "msg": {
    "best": 63,
    "id": 4
  },
  "time": "2019-02-05T18:15:40.265434+01:00"
}
{
  "time": "2019-02-05T18:15:40.453070+01:00",
  "msg": {
    "id": 12,
    "best": 63
  }
}
{
  "time": "2019-02-05T18:15:40.626988+01:00",
  "msg": {
    "id": 11,
    "best": 63
  }
}
